Metadata-Version: 2.4
Name: docmaplabs-marketing-package
Version: 0.2.1
Summary: Twitter Lead Generation + Healthcare agent (OpenRouter + Airtable) with optional FastAPI and poller
Author: Docmap.co.UK
License: MIT
Project-URL: Homepage, https://github.com/docmaplabs/docmaplabs-marketing-package
Project-URL: Repository, https://github.com/docmaplabs/docmaplabs-marketing-package
Project-URL: Issues, https://github.com/docmaplabs/docmaplabs-marketing-package/issues
Keywords: marketing,leads,healthcare,NHS,twitter,llm,openrouter,huggingface,fastapi
Classifier: Development Status :: 4 - Beta
Classifier: Intended Audience :: Developers
Classifier: Intended Audience :: Information Technology
Classifier: License :: OSI Approved :: MIT License
Classifier: Programming Language :: Python
Classifier: Programming Language :: Python :: 3
Classifier: Programming Language :: Python :: 3 :: Only
Classifier: Programming Language :: Python :: 3.11
Classifier: Topic :: Internet :: WWW/HTTP
Classifier: Topic :: Software Development :: Libraries :: Application Frameworks
Classifier: Topic :: Utilities
Requires-Python: >=3.8
License-File: LICENSE
Requires-Dist: requests>=2.31.0
Requires-Dist: requests-oauthlib>=1.3.1
Requires-Dist: pydantic>=2.7.0
Requires-Dist: python-dotenv>=1.0.1
Requires-Dist: pyairtable>=2.3.3
Provides-Extra: server
Requires-Dist: fastapi>=0.110.0; extra == "server"
Requires-Dist: uvicorn>=0.29.0; extra == "server"
Provides-Extra: rag
Requires-Dist: sentence-transformers>=2.2.2; extra == "rag"
Provides-Extra: ml
Requires-Dist: transformers>=4.40.0; extra == "ml"
Requires-Dist: torch>=2.1.0; extra == "ml"
Requires-Dist: huggingface_hub>=0.23.0; extra == "ml"
Requires-Dist: safetensors>=0.4.2; extra == "ml"
Provides-Extra: scrape
Requires-Dist: snscrape>=0.7.0.20230622; extra == "scrape"
Provides-Extra: all
Requires-Dist: fastapi>=0.110.0; extra == "all"
Requires-Dist: uvicorn>=0.29.0; extra == "all"
Requires-Dist: transformers>=4.40.0; extra == "all"
Requires-Dist: torch>=2.1.0; extra == "all"
Requires-Dist: huggingface_hub>=0.23.0; extra == "all"
Requires-Dist: safetensors>=0.4.2; extra == "all"
Requires-Dist: snscrape>=0.7.0.20230622; extra == "all"
Dynamic: license-file
